{"is_source_file": true, "format": "JavaScript (React component)", "description": "React component 'MyRecipes' that displays a list of user's recipes, allowing adding, editing, and viewing recipes. It fetches data from an API and uses React hooks for state and effects.", "external_files": ["../utils/api", "../context/UserContext", "react", "react-router-dom"], "external_methods": ["api.listRecipes", "useUser"], "published": [], "classes": [], "methods": [{"name": "MyRecipes()", "description": "React functional component that renders user's recipes list.", "scope": "", "scopeKind": ""}], "calls": ["useUser", "api.listRecipes", "setRecipes", "setLoading", "all.filter", "recipes.map"], "search-terms": ["MyRecipes", "React component", "useUser hook", "listRecipes API", "recipe list display", "hooks"], "state": 2, "file_id": 21, "knowledge_revision": 45, "git_revision": "", "ctags": [{"_type": "tag", "name": "MyRecipes", "path": "/home/kavia/workspace/code-generation/recipe-explorer-138345-138356/recipe_frontend/src/components/MyRecipes.js", "pattern": "/^export default function MyRecipes() {$/", "language": "JavaScript", "kind": "function", "signature": "()"}], "hash": "2f27a683c6ee1e2611b6f098effdeb49", "format-version": 4, "code-base-name": "recipe_frontend", "filename": "recipe_frontend/src/components/MyRecipes.js", "revision_history": [{"45": ""}]}